{
  "tabPane": [
    {
      "title": "Dashboard",
      "autoPopulate": false,
      "autoPopulatePrefix": "SmartDashboard/",
      "widgetPane": {
        "gridSize": 128.0,
        "showGrid": false,
        "hgap": 8.0,
        "vgap": 8.0,
        "titleType": 1,
        "tiles": {
          "9,0": {
            "size": [
              2,
              1
            ],
            "content": {
              "_type": "Number Slider",
              "_source0": "network_table:///SmartDashboard/Collector Speed",
              "_title": "SmartDashboard/Collector Speed",
              "_glyph": 148,
              "_showGlyph": false,
              "Slider Settings/Min": 0.0,
              "Slider Settings/Max": 1.0,
              "Slider Settings/Block increment": 0.1,
              "Visuals/Display value": true
            }
          },
          "3,0": {
            "size": [
              1,
              1
            ],
            "content": {
              "_type": "Text View",
              "_source0": "network_table:///Shuffleboard/SmartDashboard/BotHead/Value",
              "_title": "Shuffleboard/SmartDashboard/BotHead/Value",
              "_glyph": 148,
              "_showGlyph": false
            }
          },
          "4,3": {
            "size": [
              2,
              1
            ],
            "content": {
              "_type": "ComboBox Chooser",
              "_source0": "network_table:///Shuffleboard/SmartDashboard/Auto Select",
              "_title": "Auto Select",
              "_glyph": 148,
              "_showGlyph": false
            }
          },
          "6,3": {
            "size": [
              1,
              1
            ],
            "content": {
              "_type": "List Layout",
              "_title": "Timers",
              "_glyph": 149,
              "_showGlyph": false,
              "Layout/Label position": "BOTTOM",
              "_children": [
                {
                  "_type": "Text View",
                  "_source0": "network_table:///SmartDashboard/Time",
                  "_title": "Time",
                  "_glyph": 148,
                  "_showGlyph": false
                },
                {
                  "_type": "Text View",
                  "_source0": "network_table:///SmartDashboard/Timer",
                  "_title": "Timer",
                  "_glyph": 148,
                  "_showGlyph": false
                }
              ]
            }
          },
          "3,3": {
            "size": [
              1,
              1
            ],
            "content": {
              "_type": "ComboBox Chooser",
              "_source0": "network_table:///Shuffleboard/SmartDashboard/Delay",
              "_title": "Delay",
              "_glyph": 148,
              "_showGlyph": false
            }
          }
        }
      }
    }
  ],
  "windowGeometry": {
    "x": -6.400000095367432,
    "y": 0.0,
    "width": 1548.800048828125,
    "height": 693.5999755859375
  }
}